{
    "title": "AliSand Fansub",
    "name": "AliSand Fansub",
    "etag": "",
    "last_modified": "",
    "timestamp": 1517607110,
    "last_checked": 1517607108,
    "amount": 12,
    "items": [
        {
            "rtl": [
                "ar",
                "fa",
                "ur",
                "ps",
                "syr",
                "dv",
                "he",
                "yi"
            ],
            "id": "0fda6f2ed43ae0560d52c097a57cb4aa8e3826ea46fddfc430d8469b6d526672",
            "title": "Fox Spirit Matchmaker Episode 54",
            "url": "http:\/\/alisandfansub.eklablog.com\/fox-spirit-matchmaker-episode-54-a135699980",
            "author": "alisand-fansub",
            "date": {
                "date": "2018-01-20 13:21:44.000000",
                "timezone_type": 1,
                "timezone": "+01:00"
            },
            "publishedDate": {
                "date": "2018-01-20 13:21:44.000000",
                "timezone_type": 1,
                "timezone": "+01:00"
            },
            "updatedDate": {
                "date": "2018-01-20 13:21:44.000000",
                "timezone_type": 1,
                "timezone": "+01:00"
            },
            "content": "<p><a href=\"http:\/\/ekladata.com\/8MQjuQNvqi_NnXfBlY1mGcfKyPo.jpg\" rel=\"noreferrer\" target=\"_blank\"><img src=\"http:\/\/ekladata.com\/8MQjuQNvqi_NnXfBlY1mGcfKyPo@250x156.jpg\" alt=\"Fox Spirit Matchmaker Episode 54\"\/><\/a><\/p>\n<p>Coucou, <\/p>\n<p>Notre petite sortie du samedi !<\/p>\n<p>Voil\u00e0 l&#039;\u00e9pisode 54 de Fox Spirit Matchmaker !<\/p>\n<p>Je vous souhaite un bon visionnage !<\/p>\n<br\/>Article original r\u00e9dig\u00e9 par alisand-fansub et publi\u00e9 sur <a href=\"http:\/\/alisandfansub.eklablog.com\/\" rel=\"noreferrer\" target=\"_blank\">AliSand Fansub<\/a> <br\/>Reproduction interdite sans autorisation",
            "enclosureUrl": "",
            "enclosureType": "",
            "language": "fr",
            "xml": {
                "title": {},
                "link": "http:\/\/alisandfansub.eklablog.com\/fox-spirit-matchmaker-episode-54-a135699980",
                "description": {},
                "pubDate": "Sat, 20 Jan 2018 13:21:44 +0100",
                "guid": "http:\/\/alisandfansub.eklablog.com\/fox-spirit-matchmaker-episode-54-a135699980"
            },
            "namespaces": {
                "content": "http:\/\/purl.org\/rss\/1.0\/modules\/content\/",
                "dc": "http:\/\/purl.org\/dc\/elements\/1.1\/"
            }
        },
        {
            "rtl": [
                "ar",
                "fa",
                "ur",
                "ps",
                "syr",
                "dv",
                "he",
                "yi"
            ],
            "id": "eed44245b53cc0905aef4595c0f8dbccfe5dea736069a2bb7dc02ee96d8ebab1",
            "title": "Perfect Couple Episode 14",
            "url": "http:\/\/alisandfansub.eklablog.com\/perfect-couple-episode-14-a135621664",
            "author": "alisand-fansub",
            "date": {
                "date": "2018-01-15 11:45:43.000000",
                "timezone_type": 1,
                "timezone": "+01:00"
            },
            "publishedDate": {
                "date": "2018-01-15 11:45:43.000000",
                "timezone_type": 1,
                "timezone": "+01:00"
            },
            "updatedDate": {
                "date": "2018-01-15 11:45:43.000000",
                "timezone_type": 1,
                "timezone": "+01:00"
            },
            "content": "<p><a href=\"http:\/\/alisandfansub.eklablog.com\/perfect-couple-a119846916\" rel=\"noreferrer\" target=\"_blank\"><img src=\"http:\/\/ekladata.com\/TtPmiIfielmVDBzT8pnEEfCcwa0@500x267.jpg\" alt=\"Perfect Couple Episode 14\"\/><\/a><\/p>\n\n\n<p>Bonjour \u00e0 tous, <\/p>\n<p>Nous savions que ce drama \u00e9tait attendu par beaucoup d&#039;entre vous ! J&#039;avais m\u00eame eu un commentaire qui demandait si nous le faisions toujours... Alors oui, tant qu&#039;il n&#039;a pas \u00e9t\u00e9 annonc\u00e9 sur facebook ou sur le blog comme \u00e9tant abandonn\u00e9, on continue ce drama !<br\/>Comme je l&#039;ai expliqu\u00e9 dans l&#039;article mise \u00e0 jour, les v\u00e9rifications des \u00e9pisodes peuvent \u00eatre assez longues, car Julie essaie que \u00e7a colle le plus possible au sous-titres chinois, donc \u00e7a peut parfois prendre du temps ou pas en fonction des \u00e9pisodes...<br\/>Nous revoil\u00e0 enfin avec l&#039;\u00e9pisode 14 ! Le dernier \u00e9pisode \u00e9tant sorti en Ao\u00fbt 2017 &gt;.&lt;, \u00e7a doit \u00eatre notre plus grande absence sur ce drama... On fera mieux les prochains, je vous assure !<\/p>\n<p>Je vous invite \u00e0 voir l&#039;avancement des projets via votre gauche pour savoir o\u00f9 nous en sommes \u00e0 chaque fois sur ce drama. <\/p>\n<p>Sinon, parlons de cet \u00e9pisode tant attendu et j&#039;esp\u00e8re que vous \u00eates toujours au rendez-vous^^.<br\/>Une image dr\u00f4le pour reprendre &quot;en douceur&quot; Perfect Couple ! A votre avis que s&#039;est-il pass\u00e9 ? <\/p>\n<p>Et je peux vous dire qu&#039;on toujours envie de voir la suite apr\u00e8s \u00e7a !<\/p>\n<p>Bref, je vous laisse sans plus tarder avec l&#039;\u00e9pisode 14, et logiquement au mois prochain pour l&#039;\u00e9pisode 15 !<\/p>\n\n<p>Bon \u00e9pisode !<\/p>\n\n<p>(Ps : A savoir qu&#039;il n&#039;y aura pas de date exactement de sortie pour les \u00e9pisodes, \u00e7a sera dans le mois, mais \u00e7a peut \u00eatre en d\u00e9but de mois comme en fin de mois !)<\/p><br\/>Article original r\u00e9dig\u00e9 par alisand-fansub et publi\u00e9 sur <a href=\"http:\/\/alisandfansub.eklablog.com\/\" rel=\"noreferrer\" target=\"_blank\">AliSand Fansub<\/a> <br\/>Reproduction interdite sans autorisation",
            "enclosureUrl": "",
            "enclosureType": "",
            "language": "fr",
            "xml": {
                "title": {},
                "link": "http:\/\/alisandfansub.eklablog.com\/perfect-couple-episode-14-a135621664",
                "description": {},
                "pubDate": "Mon, 15 Jan 2018 11:45:43 +0100",
                "guid": "http:\/\/alisandfansub.eklablog.com\/perfect-couple-episode-14-a135621664"
            },
            "namespaces": {
                "content": "http:\/\/purl.org\/rss\/1.0\/modules\/content\/",
                "dc": "http:\/\/purl.org\/dc\/elements\/1.1\/"
            }
        },
        {
            "rtl": [
                "ar",
                "fa",
                "ur",
                "ps",
                "syr",
                "dv",
                "he",
                "yi"
            ],
            "id": "f69903ec4fd2e865a1c08efac90bb2ce9950acc11436d39e5f1a43ab5657d248",
            "title": "Love In time Episode 9 - Fin",
            "url": "http:\/\/alisandfansub.eklablog.com\/love-in-time-episode-9-fin-a135614788",
            "author": "alisand-fansub",
            "date": {
                "date": "2018-01-14 13:04:33.000000",
                "timezone_type": 1,
                "timezone": "+01:00"
            },
            "publishedDate": {
                "date": "2018-01-14 13:04:33.000000",
                "timezone_type": 1,
                "timezone": "+01:00"
            },
            "updatedDate": {
                "date": "2018-01-14 13:04:33.000000",
                "timezone_type": 1,
                "timezone": "+01:00"
            },
            "content": "<p><a href=\"http:\/\/alisandfansub.eklablog.com\/love-in-time-a132711554\" rel=\"noreferrer\" target=\"_blank\"><img src=\"http:\/\/ekladata.com\/crKuzN2Zos6Z8qPp9ZmHdgYmk2E@500x280.jpg\" alt=\"Love In time Episode 9 - Fin\"\/><\/a><\/p>\n<p>Bonjour,<\/p>\n<p>Comment allez-vous ? <\/p>\n<p>On se retrouve avec le dernier \u00e9pisode de Love In Time. Pour un dernier \u00e9pisode, il se passe encore beaucoup de choses ! Si vous attendiez le dernier \u00e9pisode pour le commencer, n&#039;h\u00e9sitez pas maintenant ! Il se regarde tout seul !<\/p>\n<p>Je remercie la team Sa Seum qui bien voulu faire cette co-prod avec nous ! Un drama sur lequel j&#039;ai ador\u00e9 travailler, ainsi que Yukina qui s&#039;est occup\u00e9e de la traduction des \u00e9pisodes de notre team !<\/p>\n<p>J&#039;aime beaucoup faire des co-prod, mais bon pas facile d&#039;en faire etc !<\/p>\n<p>Sur ce, peut-\u00eatre \u00e0 demain pour une 3i\u00e8me sortie 3 jours de suite ? ^^<\/p>\n<p>Bonne journ\u00e9e et bon \u00e9pisode !<\/p><br\/>Article original r\u00e9dig\u00e9 par alisand-fansub et publi\u00e9 sur <a href=\"http:\/\/alisandfansub.eklablog.com\/\" rel=\"noreferrer\" target=\"_blank\">AliSand Fansub<\/a> <br\/>Reproduction interdite sans autorisation",
            "enclosureUrl": "",
            "enclosureType": "",
            "language": "fr",
            "xml": {
                "title": {},
                "link": "http:\/\/alisandfansub.eklablog.com\/love-in-time-episode-9-fin-a135614788",
                "description": {},
                "pubDate": "Sun, 14 Jan 2018 13:04:33 +0100",
                "guid": "http:\/\/alisandfansub.eklablog.com\/love-in-time-episode-9-fin-a135614788"
            },
            "namespaces": {
                "content": "http:\/\/purl.org\/rss\/1.0\/modules\/content\/",
                "dc": "http:\/\/purl.org\/dc\/elements\/1.1\/"
            }
        },
        {
            "rtl": [
                "ar",
                "fa",
                "ur",
                "ps",
                "syr",
                "dv",
                "he",
                "yi"
            ],
            "id": "a3c129927c80e917e1e04021cb348fec2ac68b0ce5253d7e61ca2715ae675512",
            "title": "Fox Spirit Matchmaker Episode 53",
            "url": "http:\/\/alisandfansub.eklablog.com\/fox-spirit-matchmaker-episode-53-a135592182",
            "author": "alisand-fansub",
            "date": {
                "date": "2018-01-13 10:56:52.000000",
                "timezone_type": 1,
                "timezone": "+01:00"
            },
            "publishedDate": {
                "date": "2018-01-13 10:56:52.000000",
                "timezone_type": 1,
                "timezone": "+01:00"
            },
            "updatedDate": {
                "date": "2018-01-13 10:56:52.000000",
                "timezone_type": 1,
                "timezone": "+01:00"
            },
            "content": "<p><a href=\"http:\/\/ekladata.com\/8MQjuQNvqi_NnXfBlY1mGcfKyPo.jpg\" rel=\"noreferrer\" target=\"_blank\"><img src=\"http:\/\/ekladata.com\/8MQjuQNvqi_NnXfBlY1mGcfKyPo@250x156.jpg\" alt=\"Fox Spirit Matchmaker Episode 53\"\/><\/a><\/p>\n\n<p>Bonjour, <\/p>\n<p>Presque deux semaines sans nouvelle sortie pour Fox Spirit Matchmaker, mais vous aviez \u00e9t\u00e9 pr\u00e9venu !<\/p>\n<p>Nous revoil\u00e0 avec l&#039;\u00e9pisode 53 !<\/p>\n<p>J&#039;esp\u00e8re que nos h\u00e9ros vous on manquez ! Et retrouvez-les samedi prochain !<\/p>\n<p>Bonne journ\u00e9e !<\/p><br\/>Article original r\u00e9dig\u00e9 par alisand-fansub et publi\u00e9 sur <a href=\"http:\/\/alisandfansub.eklablog.com\/\" rel=\"noreferrer\" target=\"_blank\">AliSand Fansub<\/a> <br\/>Reproduction interdite sans autorisation",
            "enclosureUrl": "",
            "enclosureType": "",
            "language": "fr",
            "xml": {
                "title": {},
                "link": "http:\/\/alisandfansub.eklablog.com\/fox-spirit-matchmaker-episode-53-a135592182",
                "description": {},
                "pubDate": "Sat, 13 Jan 2018 10:56:52 +0100",
                "guid": "http:\/\/alisandfansub.eklablog.com\/fox-spirit-matchmaker-episode-53-a135592182"
            },
            "namespaces": {
                "content": "http:\/\/purl.org\/rss\/1.0\/modules\/content\/",
                "dc": "http:\/\/purl.org\/dc\/elements\/1.1\/"
            }
        },
        {
            "rtl": [
                "ar",
                "fa",
                "ur",
                "ps",
                "syr",
                "dv",
                "he",
                "yi"
            ],
            "id": "fe72dbfff123743952f9351dd872b79b2ab77a99865537348bee00c36e7107cf",
            "title": "Mise au point (avancements, projets etc...)",
            "url": "http:\/\/alisandfansub.eklablog.com\/mise-au-point-avancements-projets-etc-a135326334",
            "author": "alisand-fansub",
            "date": {
                "date": "2018-01-10 12:51:13.000000",
                "timezone_type": 1,
                "timezone": "+01:00"
            },
            "publishedDate": {
                "date": "2018-01-10 12:51:13.000000",
                "timezone_type": 1,
                "timezone": "+01:00"
            },
            "updatedDate": {
                "date": "2018-01-10 12:51:13.000000",
                "timezone_type": 1,
                "timezone": "+01:00"
            },
            "content": "<p>Coucou, <\/p>\n<p>J&#039;avais fait un article du m\u00eame genre il y a deux ans, et je ne sais plus pourquoi je ne l&#039;avais pas fait en 2017, mais bref, ce n&#039;est pas tr\u00e8s grave ! <\/p>\n<p>Nouvelle ann\u00e9e dit changement, mise au point et tout le reste dans le m\u00eame genre !<\/p>\n<p>Voil\u00e0 nos projets en cours et futurs avec des petites explications pour certains.<\/p>\n\n\n\n<p>Niveau projets, on a quoi a vous proposer pour le moment :<\/p>\n\n<p>- <a href=\"http:\/\/alisandfansub.eklablog.com\/perfect-couple-a119846916\" rel=\"noreferrer\" target=\"_blank\">Perfect Couple<\/a> : En 2017, seulement 5 \u00e9pisodes de ce drama sont sortis... Bouh, j&#039;aurais tellement voulu vous en sortir plus... Logiquement pour no\u00ebl et nouvel an, vous auriez d\u00fb avoir les \u00e9pisodes 14 et 15... Mais bon, vous aurez au moins l&#039;\u00e9pisode 14 ce mois de janvier !<\/p>\n<p>Objectif pour ce drama : 12 \u00e9pisodes par an, donc 1 \u00e9pisode par mois. Ca peut ne pas \u00eatre beaucoup, mais ce drama demande beaucoup de v\u00e9rifications avec les sous-titres chinois. Pourtant ce ne sont pas les \u00e9pisodes que nous avons traduits d&#039;avance pour ce drama ! M\u00eame si je n&#039;ai plus de nouvelle de celle qui fait l&#039;\u00e9pisode 15... (on a toujours un souci avec nos projets de toute fa\u00e7on XD)<\/p>\n\n<p>- <a href=\"http:\/\/alisandfansub.eklablog.com\/general-and-i-a129296516\" rel=\"noreferrer\" target=\"_blank\">General And I<\/a> (partie vip) : Le petit coup de coeur de la team de l&#039;ann\u00e9e 2017 ! On a pas sorti \u00e9norm\u00e9ment d&#039;\u00e9pisodes : 15 \u00e9pisodes cette ann\u00e9e, m\u00eame si 2 \u00e9pisodes de plus auraient d\u00fb sortir pour no\u00ebl\/nouvel an. Je dois dire que je ne sais pas \u00e0 quelle fr\u00e9quence on sortira les \u00e9pisodes, mais environ toutes les deux semaines car Laetitia devrait revenir ce mois-ci ! <\/p>\n\n<p>- <a href=\"http:\/\/alisandfansub.eklablog.com\/fox-spirit-matchmaker-huyao-xiao-hongniang-a126687020\" rel=\"noreferrer\" target=\"_blank\">Fox Spirit Matchmaker<\/a> : Pas grand chose \u00e0 dire sur ce projet, si ce n&#039;est que nous en sommes \u00e0 la saison 5 et que les \u00e9pisodes sortent petit \u00e0 petit ^^<\/p>\n\n<p>- <a href=\"http:\/\/alisandfansub.eklablog.com\/\/Too%20late%20to%20say%20I%20love%20you\" rel=\"noreferrer\" target=\"_blank\">Too Late to Say I Love you<\/a> : Un drama commenc\u00e9 en fin d&#039;ann\u00e9e 2017, donc pour le moment que deux \u00e9pisodes de sortis. On esp\u00e8re \u00e9galement sortir 1 \u00e9pisode toutes les deux semaines.<\/p>\n\n<p>Je tiens \u00e0 pr\u00e9ciser, m\u00eame si un drama ne sort pas r\u00e9guli\u00e8rement, \u00e7a ne veut pas dire que les \u00e9pisodes n&#039;avancent pas. On avance petit \u00e0 petit dans l&#039;ombre \u00e0 notre rythme^^.<br\/>Les avancements sont mis r\u00e9guli\u00e8rement \u00e0 jour. Donc il n&#039;y a pas besoin de nous demander si tel ou tel projet est arr\u00eat\u00e9 ou pas. Si cela n&#039;a pas \u00e9t\u00e9 annonc\u00e9 sur le blog ou facebook le projet est toujours en cours.<\/p>\n\n<p>Projets futurs :<\/p>\n\n<p>- <a href=\"http:\/\/alisandfansub.eklablog.com\/chinese-paladin-5-clouds-of-the-world-a127842180\" rel=\"noreferrer\" target=\"_blank\">Chinese Paladin 5<\/a> : Comme vous le savez nous avons d\u00e9j\u00e0 3 drama avec pas mal d&#039;\u00e9pisodes, nous ne pouvons pas en commencer un quatri\u00e8me, mais si nous pouvons le commencer cette ann\u00e9e, \u00e7a serait super (surement en fin d&#039;ann\u00e9e)<\/p>\n\n<p>-  <a href=\"http:\/\/alisandfansub.eklablog.com\/days-we-stared-at-the-sun-a119846978\" rel=\"noreferrer\" target=\"_blank\">Days we stared at the sun<\/a> (partie vip) : Dans les projets de la team depuis 2 ans, voir un peu plus m\u00eame ! Il aurait d\u00fb sortir en d\u00e9cembre 2017, mais finalement \u00e7a ne s&#039;est pas fait ! Mais en 2018, sur vous l&#039;aurez. Donc s&#039;il vous int\u00e9resse, restez vigilants (fin d&#039;ann\u00e9e, je pense)<\/p>\n\n<p>- Des id\u00e9es de quelques films\/sp \u00e0 faire ! Il faut juste qu&#039;on se mette d&#039;accord ^^ (dans les prochains jours surement la liste des projets surprises devrait s&#039;allonger lol).<br\/>Mais si vous avez des id\u00e9es de drama (court) ou films n&#039;h\u00e9sitez pas \u00e0 nous en faire part \u00e9galement !<\/p>\n\n<p>R\u00e9solution pour cette ann\u00e9e 2018 ^^:<\/p>\n<p>- Pouvoir faire d&#039;autres co-prod avec d&#039;autres teams de fansub <\/p>\n<p>- Pouvoir faire un calendrier de l&#039;avant pour no\u00ebl ^^ (une sortie par jour pendant le mois de d\u00e9cembre : \u00e9pisode de drama en cours, sp, films, nouveaux drama) <\/p>\n<p>- Des id\u00e9es ? ^^<\/p>\n\n<p>Sur ce, \u00e0 tr\u00e8s bient\u00f4t et nous esp\u00e9rons que ce petit article vous aide \u00e0 y voir plus clair, etc...<\/p><br\/>Article original r\u00e9dig\u00e9 par alisand-fansub et publi\u00e9 sur <a href=\"http:\/\/alisandfansub.eklablog.com\/\" rel=\"noreferrer\" target=\"_blank\">AliSand Fansub<\/a> <br\/>Reproduction interdite sans autorisation",
            "enclosureUrl": "",
            "enclosureType": "",
            "language": "fr",
            "xml": {
                "title": {},
                "link": "http:\/\/alisandfansub.eklablog.com\/mise-au-point-avancements-projets-etc-a135326334",
                "description": {},
                "pubDate": "Wed, 10 Jan 2018 12:51:13 +0100",
                "guid": "http:\/\/alisandfansub.eklablog.com\/mise-au-point-avancements-projets-etc-a135326334"
            },
            "namespaces": {
                "content": "http:\/\/purl.org\/rss\/1.0\/modules\/content\/",
                "dc": "http:\/\/purl.org\/dc\/elements\/1.1\/"
            }
        },
        {
            "rtl": [
                "ar",
                "fa",
                "ur",
                "ps",
                "syr",
                "dv",
                "he",
                "yi"
            ],
            "id": "d870ce24d703f50a6b56db02547aa898afdc987eb99cb6f8350a9834f90b3e97",
            "title": "Nouvel An = petits cadeaux !",
            "url": "http:\/\/alisandfansub.eklablog.com\/nouvel-an-petits-cadeaux-a135325448",
            "author": "alisand-fansub",
            "date": {
                "date": "2017-12-31 20:51:01.000000",
                "timezone_type": 1,
                "timezone": "+01:00"
            },
            "publishedDate": {
                "date": "2017-12-31 20:51:01.000000",
                "timezone_type": 1,
                "timezone": "+01:00"
            },
            "updatedDate": {
                "date": "2017-12-31 20:51:01.000000",
                "timezone_type": 1,
                "timezone": "+01:00"
            },
            "content": "<p>Coucou,<\/p>\n<p>Tout d&#039;abord, nous esp\u00e9rons que vous avez pass\u00e9 un bon r\u00e9veillon de nouvel an, que se soit avec vos amis ou votre famille !<\/p>\n<p>Comme chacun ann\u00e9e, on essaie de faire quelques surprises pour le premier jour de l&#039;ann\u00e9e car il faut bien commencer l&#039;ann\u00e9e sur de bonnes bases lol^^.<\/p>\n\n<p><strong>Premi\u00e8re surprise :<\/strong> Fox Spirit Matchmaker Episode 52 <\/p>\n\n<p><a href=\"http:\/\/ekladata.com\/8MQjuQNvqi_NnXfBlY1mGcfKyPo.jpg\" rel=\"noreferrer\" target=\"_blank\"><img src=\"http:\/\/ekladata.com\/8MQjuQNvqi_NnXfBlY1mGcfKyPo@250x156.jpg\" alt=\"Nouvel An = petits cadeaux !\"\/><\/a><\/p>\n\n<p>On commence par l&#039;anime chinois, Fox Spirit Matchmaker avec l&#039;\u00e9pisode 52 ! <\/p>\n<p>Vu que les f\u00eates de fin d&#039;ann\u00e9e sont finies, les sorties de l&#039;anime reprendront comme avant avec un \u00e9pisode chaque samedi (sauf samedi 6 janvier, merci de votre compr\u00e9hension. Donc \u00e9pisode 53, le 13 janvier !)<\/p>\n<p><strong>Deuxi\u00e8me surprise :<\/strong> <a href=\"http:\/\/alisandfansub.eklablog.com\/lady-of-the-dynasty-a132678678\" rel=\"noreferrer\" target=\"_blank\">Lady of the Dynasty - Film chinois<\/a><\/p>\n<p><a href=\"http:\/\/ekladata.com\/SWi0BjqiaKCB_Kcm1ePz8JSSHwI.jpg\" rel=\"noreferrer\" target=\"_blank\"><img src=\"http:\/\/ekladata.com\/SWi0BjqiaKCB_Kcm1ePz8JSSHwI@167x232.jpg\" alt=\"Nouvel An = petits cadeaux !\"\/><\/a><\/p>\n\n<p>Un film qui aurait d\u00fb sortir pour no\u00ebl, mais nous avons eu un petit souci &gt;.&lt;.<br\/>C&#039;est pas vraiment un film \u00e0 voir en p\u00e9riode de f\u00eates, il est bien dramatique comme film.<br\/>Nous esp\u00e9rons que vous aimerez tout de m\u00eame.<\/p>\n\n<p><strong>Troisi\u00e8me surprise :<\/strong> Love In Time Episode 8<\/p>\n<p><a href=\"http:\/\/ekladata.com\/msP0h7BTyEFNyyChsGK_Tndt6_0.jpg\" rel=\"noreferrer\" target=\"_blank\"><img src=\"http:\/\/ekladata.com\/msP0h7BTyEFNyyChsGK_Tndt6_0@500x274.jpg\" alt=\"Nouvel An = petits cadeaux !\"\/><\/a><\/p>\n\n<p>Pendant toute la semaine derni\u00e8re, on s&#039;est retrouv\u00e9 une fois tous les jours pour un \u00e9pisode de ce drama !<\/p>\n<p>Je l&#039;aime toujours autant et j&#039;ai h\u00e2te de voir l&#039;\u00e9pisode 9 !<\/p>\n<p>Je ne sais pas quand arrivera l&#039;\u00e9pisode 9. Il aurait du sortir aujourd&#039;hui, mais nous n&#039;avons pas eu le temps de nous en occuper. Mais ne vous inqui\u00e9tez pas, il arrivera en Janvier^^.<\/p>\n\n<p><strong>Quatri\u00e8me surprise et la derni\u00e8re :<\/strong> Too Late to Say I love you Episode 2<\/p>\n<p><a href=\"http:\/\/ekladata.com\/6bQQixYBYbZRrlDBgpktl7CXJCU.jpg\" rel=\"noreferrer\" target=\"_blank\"><img src=\"http:\/\/ekladata.com\/6bQQixYBYbZRrlDBgpktl7CXJCU@500x216.jpg\" alt=\"Nouvel An = petits cadeaux !\"\/><\/a><\/p>\n\n<p>Le premier \u00e9pisode \u00e9tant sorti pour no\u00ebl, voil\u00e0 l&#039;\u00e9pisode 2 pour ce premier jour de l&#039;ann\u00e9e !<\/p>\n<p>Concernant ce drama, je ne sais pas trop \u00e0 quelle fr\u00e9quence les \u00e9pisodes sortiront, mais je pense que se sera un \u00e9pisode toutes les deux semaines.<br\/>Sur ce nous vous souhaitons \u00e0 tous une tr\u00e8s bonne ann\u00e9e 2018 et une bonne sant\u00e9 et que vos voeux vous soit r\u00e9aliser.<\/p>\n\n<p>(d\u00e9sol\u00e9, l&#039;article \u00e0 \u00e9t\u00e9 mis en ligne le 31 d\u00e9cembre alors qu&#039;il aurait d\u00fb arriver le 1er janvier, s\u00fbrement une mauvaise manipulation)<\/p><br\/>Article original r\u00e9dig\u00e9 par alisand-fansub et publi\u00e9 sur <a href=\"http:\/\/alisandfansub.eklablog.com\/\" rel=\"noreferrer\" target=\"_blank\">AliSand Fansub<\/a> <br\/>Reproduction interdite sans autorisation",
            "enclosureUrl": "",
            "enclosureType": "",
            "language": "fr",
            "xml": {
                "title": {},
                "link": "http:\/\/alisandfansub.eklablog.com\/nouvel-an-petits-cadeaux-a135325448",
                "description": {},
                "pubDate": "Sun, 31 Dec 2017 20:51:01 +0100",
                "guid": "http:\/\/alisandfansub.eklablog.com\/nouvel-an-petits-cadeaux-a135325448"
            },
            "namespaces": {
                "content": "http:\/\/purl.org\/rss\/1.0\/modules\/content\/",
                "dc": "http:\/\/purl.org\/dc\/elements\/1.1\/"
            }
        },
        {
            "rtl": [
                "ar",
                "fa",
                "ur",
                "ps",
                "syr",
                "dv",
                "he",
                "yi"
            ],
            "id": "5c8671cc2d52e16ca69edc9ee61a295abdba43e610d44acfa1a65824faa3253d",
            "title": "Love In Time Episode 6 et 7",
            "url": "http:\/\/alisandfansub.eklablog.com\/love-in-time-episode-6-et-7-a135325308",
            "author": "alisand-fansub",
            "date": {
                "date": "2017-12-30 15:31:17.000000",
                "timezone_type": 1,
                "timezone": "+01:00"
            },
            "publishedDate": {
                "date": "2017-12-30 15:31:17.000000",
                "timezone_type": 1,
                "timezone": "+01:00"
            },
            "updatedDate": {
                "date": "2017-12-30 15:31:17.000000",
                "timezone_type": 1,
                "timezone": "+01:00"
            },
            "content": "<p><a href=\"http:\/\/ekladata.com\/7YSL8Nlau1HITXRlI0N1eBZl_i4.jpg\" rel=\"noreferrer\" target=\"_blank\"><img src=\"http:\/\/ekladata.com\/7YSL8Nlau1HITXRlI0N1eBZl_i4@500x232.jpg\" alt=\"Love In Time Episode 6 et 7\"\/><\/a><\/p>\n\n<p><a href=\"http:\/\/ekladata.com\/pYKNBX6JF63HyeGi1gmjQ447xxE.jpg\" rel=\"noreferrer\" target=\"_blank\"><img src=\"http:\/\/ekladata.com\/pYKNBX6JF63HyeGi1gmjQ447xxE@500x266.jpg\" alt=\"Love In Time Episode 6 et 7\"\/><\/a><\/p>\n\n<p>Coucou, <\/p>\n<p>Nous revoil\u00e0 avec la suite de Love in Time, non pas un mais deux \u00e9pisodes ! <\/p>\n<p>Je ne sais pas si j&#039;aurais le temps de sortir l&#039;\u00e9pisode 7 demain avec le r\u00e9veillon de nouvel an, du coup, vous l&#039;avez un jour en avance^^.<br\/>Ce drama n&#039;est pas concentr\u00e9 sur le couple Roy et Lok Hei Lam, dans les \u00e9pisodes 6 et 7 George et Mei Loi sont un peu plus pr\u00e9sent mais je n&#039;en dis pas plus ! <\/p>\n<p>Et dans l&#039;\u00e9pisode 7, une d\u00e9couverte pour Ngai Saam qui apprend la v\u00e9rit\u00e9 !<\/p>\n<p>Bref, bon visionnage !<\/p>\n\n<p>A bient\u00f4t <\/p>\n\n<p>Ps : je vous souhaite un bon r\u00e9veillon de nouvel an !<\/p>\n\n\n<br\/>Article original r\u00e9dig\u00e9 par alisand-fansub et publi\u00e9 sur <a href=\"http:\/\/alisandfansub.eklablog.com\/\" rel=\"noreferrer\" target=\"_blank\">AliSand Fansub<\/a> <br\/>Reproduction interdite sans autorisation",
            "enclosureUrl": "",
            "enclosureType": "",
            "language": "fr",
            "xml": {
                "title": {},
                "link": "http:\/\/alisandfansub.eklablog.com\/love-in-time-episode-6-et-7-a135325308",
                "description": {},
                "pubDate": "Sat, 30 Dec 2017 15:31:17 +0100",
                "guid": "http:\/\/alisandfansub.eklablog.com\/love-in-time-episode-6-et-7-a135325308"
            },
            "namespaces": {
                "content": "http:\/\/purl.org\/rss\/1.0\/modules\/content\/",
                "dc": "http:\/\/purl.org\/dc\/elements\/1.1\/"
            }
        },
        {
            "rtl": [
                "ar",
                "fa",
                "ur",
                "ps",
                "syr",
                "dv",
                "he",
                "yi"
            ],
            "id": "377d4d37e3c8e0934686dc3d55d190c26b01df300562c67cb94680418f18cef4",
            "title": "Love in Time Episode 5",
            "url": "http:\/\/alisandfansub.eklablog.com\/love-in-time-episode-5-a135314604",
            "author": "alisand-fansub",
            "date": {
                "date": "2017-12-29 15:11:25.000000",
                "timezone_type": 1,
                "timezone": "+01:00"
            },
            "publishedDate": {
                "date": "2017-12-29 15:11:25.000000",
                "timezone_type": 1,
                "timezone": "+01:00"
            },
            "updatedDate": {
                "date": "2017-12-29 15:11:25.000000",
                "timezone_type": 1,
                "timezone": "+01:00"
            },
            "content": "<p><a href=\"http:\/\/ekladata.com\/_PZagVtldRfEaLC3hblUv9w8cb0.jpg\" rel=\"noreferrer\" target=\"_blank\"><img src=\"http:\/\/ekladata.com\/_PZagVtldRfEaLC3hblUv9w8cb0@500x262.jpg\" alt=\"Love in Time Episode 5\"\/><\/a><\/p>\n\n<p>Coucou,<\/p>\n<p>Notre petite sortie du jour !<\/p>\n<p>Cette fois-ci, \u00e9pisode 5 de Love in Time !<br\/>Un \u00e9pisode o\u00f9 il se passe beaucoup de choses !<br\/><\/p>\n<p>Les sentiments de nos personnages principaux sont mis \u00e0 l&#039;\u00e9preuve dedans ! Je ne vous en dis pas plus et je vous laisse d\u00e9couvrir cet \u00e9pisode par vous-m\u00eames !<\/p>\n<p>Merci pour tous vos commentaires sur ce drama ! Je ne r\u00e9ponds pas \u00e0 tout le monde vu que je r\u00e9p\u00e9terais souvent la m\u00eame chose, mais vos commentaires nous font plaisir^^.<\/p>\n<p>A demain et bon \u00e9pisode !<\/p><br\/>Article original r\u00e9dig\u00e9 par alisand-fansub et publi\u00e9 sur <a href=\"http:\/\/alisandfansub.eklablog.com\/\" rel=\"noreferrer\" target=\"_blank\">AliSand Fansub<\/a> <br\/>Reproduction interdite sans autorisation",
            "enclosureUrl": "",
            "enclosureType": "",
            "language": "fr",
            "xml": {
                "title": {},
                "link": "http:\/\/alisandfansub.eklablog.com\/love-in-time-episode-5-a135314604",
                "description": {},
                "pubDate": "Fri, 29 Dec 2017 15:11:25 +0100",
                "guid": "http:\/\/alisandfansub.eklablog.com\/love-in-time-episode-5-a135314604"
            },
            "namespaces": {
                "content": "http:\/\/purl.org\/rss\/1.0\/modules\/content\/",
                "dc": "http:\/\/purl.org\/dc\/elements\/1.1\/"
            }
        },
        {
            "rtl": [
                "ar",
                "fa",
                "ur",
                "ps",
                "syr",
                "dv",
                "he",
                "yi"
            ],
            "id": "b3104da50bf002285615f5c2d40c5330273aafed8830a1ef855ce0a8443c012e",
            "title": "Love In time Episode 4",
            "url": "http:\/\/alisandfansub.eklablog.com\/love-in-time-episode-4-a135310154",
            "author": "alisand-fansub",
            "date": {
                "date": "2017-12-28 16:01:15.000000",
                "timezone_type": 1,
                "timezone": "+01:00"
            },
            "publishedDate": {
                "date": "2017-12-28 16:01:15.000000",
                "timezone_type": 1,
                "timezone": "+01:00"
            },
            "updatedDate": {
                "date": "2017-12-28 16:01:15.000000",
                "timezone_type": 1,
                "timezone": "+01:00"
            },
            "content": "<p><a href=\"http:\/\/ekladata.com\/jsJonOT5TEw7OGVKUZl1IxTcErc.jpg\" rel=\"noreferrer\" target=\"_blank\"><img src=\"http:\/\/ekladata.com\/jsJonOT5TEw7OGVKUZl1IxTcErc@500x263.jpg\" alt=\"Love In time Episode 4\"\/><\/a><\/p>\n<p>Coucou, <\/p>\n<p>Comment allez-vous depuis hier ? <br\/>Merci pour vos nombreux commentaires ! Nous sommes heureuses que ce petit drama vous plaise ! M\u00eame si on a pas eu beaucoup de retour sur celui-ci ! J&#039;aime beaucoup ! <\/p>\n<p>Un \u00e9pisode qui se regarde tranquillement ! Mais qui changera sur la fin ! Et je peux vous assurer que cette fin donne envie de voir la suite ! Que va-t-il se passer pour Roy et Hei Lam ? La v\u00e9rit\u00e9 d\u00e9couverte sur Roy ? Tout \u00e7a au prochain \u00e9pisode !<\/p>\n<p>Sinon, j&#039;aime bien les passages avec George ! Il est assez dr\u00f4le par moment ^^.<\/p>\n\n<p>A demain pour la suite ^^<\/p>\n<br\/>Article original r\u00e9dig\u00e9 par alisand-fansub et publi\u00e9 sur <a href=\"http:\/\/alisandfansub.eklablog.com\/\" rel=\"noreferrer\" target=\"_blank\">AliSand Fansub<\/a> <br\/>Reproduction interdite sans autorisation",
            "enclosureUrl": "",
            "enclosureType": "",
            "language": "fr",
            "xml": {
                "title": {},
                "link": "http:\/\/alisandfansub.eklablog.com\/love-in-time-episode-4-a135310154",
                "description": {},
                "pubDate": "Thu, 28 Dec 2017 16:01:15 +0100",
                "guid": "http:\/\/alisandfansub.eklablog.com\/love-in-time-episode-4-a135310154"
            },
            "namespaces": {
                "content": "http:\/\/purl.org\/rss\/1.0\/modules\/content\/",
                "dc": "http:\/\/purl.org\/dc\/elements\/1.1\/"
            }
        },
        {
            "rtl": [
                "ar",
                "fa",
                "ur",
                "ps",
                "syr",
                "dv",
                "he",
                "yi"
            ],
            "id": "696050b8d0846de4683436abfd79da308e863c2e0125bae8623107c912d710b7",
            "title": "Love In Time Episode 2 et 3",
            "url": "http:\/\/alisandfansub.eklablog.com\/love-in-time-episode-2-et-3-a135295000",
            "author": "alisand-fansub",
            "date": {
                "date": "2017-12-27 15:58:11.000000",
                "timezone_type": 1,
                "timezone": "+01:00"
            },
            "publishedDate": {
                "date": "2017-12-27 15:58:11.000000",
                "timezone_type": 1,
                "timezone": "+01:00"
            },
            "updatedDate": {
                "date": "2017-12-27 15:58:11.000000",
                "timezone_type": 1,
                "timezone": "+01:00"
            },
            "content": "<p><a href=\"http:\/\/alisandfansub.eklablog.com\/love-in-time-a132711554\" rel=\"noreferrer\" target=\"_blank\"><img src=\"http:\/\/ekladata.com\/w9KMIAs1QK2wn9aS4IGpOhBPu9U@500x259.jpg\" alt=\"Love In Time Episode 2 et 3\"\/><\/a><\/p>\n\n<p><a href=\"http:\/\/alisandfansub.eklablog.com\/love-in-time-a132711554\" rel=\"noreferrer\" target=\"_blank\"><img src=\"http:\/\/ekladata.com\/fmW-wvRjq3EMB3nIDiviycQZ6Oc@500x284.jpg\" alt=\"Love In Time Episode 2 et 3\"\/><\/a><\/p>\n<p>Coucou,<\/p>\n<p>Je n&#039;ai pas eu le temps de sortir l&#039;\u00e9pisode 2 hier, mais le voil\u00e0 aujourd&#039;hui avec l&#039;\u00e9pisode 3 en plus^^<br\/>Nous esp\u00e9rons que vous avez appr\u00e9ci\u00e9 le premier \u00e9pisode et que vous avez h\u00e2te de savoir ce qui se passe dans les prochains \u00e9pisodes !<\/p>\n<p>Un drama qui ne paye pas de mine comme \u00e7a, mais qui finalement on s&#039;attache tr\u00e8s rapidement aux personnages de ce petit drama !<\/p>\n<p>Episode 2 sympa qui nous permet de d\u00e9couvrir un personnage peu mis en avant au d\u00e9but et qui va rejoindre nos personnages dans le judo !<br\/>Et la fin de cet \u00e9pisode donne envie d&#039;encha\u00eener sur la suite !<\/p>\n\n<p>L&#039;\u00e9pisode 3 avec l&#039;anniversaire de Roy ! Je dois dire que j&#039;ai ador\u00e9 ce passage ! Trop mignon !<\/p>\n\n<p>Bref, je vous laisse sans plus tarder avec ces deux \u00e9pisodes ! <br\/>Nous attendons, bien entendu, vos avis sur ces \u00e9pisodes !<\/p>\n<p>Bonne journ\u00e9e !<\/p><br\/>Article original r\u00e9dig\u00e9 par alisand-fansub et publi\u00e9 sur <a href=\"http:\/\/alisandfansub.eklablog.com\/\" rel=\"noreferrer\" target=\"_blank\">AliSand Fansub<\/a> <br\/>Reproduction interdite sans autorisation",
            "enclosureUrl": "",
            "enclosureType": "",
            "language": "fr",
            "xml": {
                "title": {},
                "link": "http:\/\/alisandfansub.eklablog.com\/love-in-time-episode-2-et-3-a135295000",
                "description": {},
                "pubDate": "Wed, 27 Dec 2017 15:58:11 +0100",
                "guid": "http:\/\/alisandfansub.eklablog.com\/love-in-time-episode-2-et-3-a135295000"
            },
            "namespaces": {
                "content": "http:\/\/purl.org\/rss\/1.0\/modules\/content\/",
                "dc": "http:\/\/purl.org\/dc\/elements\/1.1\/"
            }
        }
    ]
}